mmurtha4_new_synpyosys_test/DesignC.py
mmurtha4_new_synpyosys_test/DesignTemp.py
mmurtha4_new_synpyosys_test/ModuleC.py
mmurtha4_new_synpyosys_test/ModuleClass.py
mmurtha4_new_synpyosys_test/ModuleCls.py
mmurtha4_new_synpyosys_test/ModuleTemplate.py
mmurtha4_new_synpyosys_test/__init__.py
mmurtha4_new_synpyosys_test/example.py
mmurtha4_new_synpyosys_test-0.0.2.dist-info/METADATA
mmurtha4_new_synpyosys_test-0.0.2.dist-info/WHEEL
mmurtha4_new_synpyosys_test-0.0.2.dist-info/licenses/LICENSE
mmurtha4_new_synpyosys_test-0.0.2.dist-info/RECORD
