Metadata-Version: 2.1
Name: mmurtha4_new_synpyosys_test
Version: 0.0.2
Summary: Test package for SynPYosys
Project-URL: Homepage, https://github.com/pypa/sampleproject
Project-URL: Bug Tracker, https://github.com/pypa/sampleproject/issues
Author-email: Mitchell Murtha <mmurtha4@villanova.edu>
License: Copyright (c) 2018 The Python Packaging Authority
Classifier: License :: OSI Approved :: MIT License
Classifier: Operating System :: OS Independent
Classifier: Programming Language :: Python :: 2
Requires-Python: >=2.7
